LICENSE
MANIFEST.in
README.md
README.txt
requirements.txt
setup.py
bin/es_bash_completion
elasticsearch_fabric.egg-info/PKG-INFO
elasticsearch_fabric.egg-info/SOURCES.txt
elasticsearch_fabric.egg-info/dependency_links.txt
elasticsearch_fabric.egg-info/requires.txt
elasticsearch_fabric.egg-info/top_level.txt
esfabric/__init__.py
esfabric/tasks/__init__.py
esfabric/tasks/cat.py
esfabric/tasks/cluster.py
esfabric/tasks/helpers.py
esfabric/tasks/indices.py
esfabric/tasks/nodes.py
esfabric/tasks/snapshot.py
esfabric/tasks/utils.py