Metadata-Version: 1.1
Name: elasticsearch-fabric
Version: 0.1.5
Summary: This package provides a unified command line interface to Elasticsearch in Fabric.
Home-page: https://github.com/KunihikoKido/elasticsearch-fabric
Author: Kunihiko Kido
Author-email: kunihiko.kido@me.com
License: MIT
Keywords: elasticsearch,fabric
Platform: OS Independent
Classifier: Intended Audience :: Developers
Classifier: License :: OSI Approved :: MIT License
Classifier: Operating System :: OS Independent
Classifier: Programming Language :: Python
Classifier: Topic :: Software Development :: Libraries :: Python Modules
Classifier: Programming Language :: Python :: 2.7
